SoftEtherClient/__init__.py
SoftEtherClient/errors.py
SoftEtherClient/main.py
SoftEtherClient/models.py
SoftEtherClient/parser.py
pySoftEtherClient-0.0.0.1.dist-info/METADATA
pySoftEtherClient-0.0.0.1.dist-info/WHEEL
pySoftEtherClient-0.0.0.1.dist-info/top_level.txt
pySoftEtherClient-0.0.0.1.dist-info/RECORD
