Metadata-Version: 2.1
Name: pySoftEtherClient
Version: 0.0.0.1
Summary: SoftEther Client API
Home-page: https://github.com/fazalfarhan01/SoftEtherClient-API
Author: fazalfarhan01 (Mohamed Farhan Fazal)
Author-email: fazal@ffehost.com
License: UNKNOWN
Project-URL: Bug Tracker, https://github.com/fazalfarhan01/SoftEtherClient-API/issues
Keywords: python,softether,vpn,vpngate,requests,python softetherclient,SoftEtherClient API,pySoftEtherClient
Platform: UNKNOWN
Classifier: Development Status :: 5 - Production/Stable
Classifier: Intended Audience :: Developers
Classifier: Programming Language :: Python :: 3
Classifier: Operating System :: OS Independent
Requires-Dist: requests
